task_processor/__init__.py
task_processor/__main__.py
task_processor/core/__init__.py
task_processor/core/executor.py
task_processor/core/models.py
task_processor/core/scheduler.py
task_processor/core/executor/task_executor.py
task_processor/core/models/config.py
task_processor/core/models/database.py
task_processor/core/models/task.py
task_processor/core/scheduler/task_scheduler.py
task_processor/plugins/__init__.py
task_processor/plugins/base.py
task_processor/plugins/http/__init__.py
task_processor/plugins/mysql/__init__.py
task_processor/plugins/mysql/plugin.py
task_processor/plugins/postgres/__init__.py
task_processor/plugins/redis/__init__.py
task_processor/utils/__init__.py
task_processor/utils/config_loader.py
task_processor/utils/logging.py
taskops-0.1.7.dist-info/licenses/LICENSE
tests/conftest.py
tests/test_task_processor.py
taskops-0.1.7.dist-info/METADATA
taskops-0.1.7.dist-info/WHEEL
taskops-0.1.7.dist-info/entry_points.txt
taskops-0.1.7.dist-info/top_level.txt
taskops-0.1.7.dist-info/RECORD
