Metadata-Version: 2.4
Name: taskops
Version: 0.1.7
Summary: A flexible task scheduling and execution framework
Home-page: https://github.com/sharik709/task-runner
Author: Sharik Shaikh
Author-email: Sharik Shaikh <shaikhsharik709@gmail.com>
License: MIT
Project-URL: Homepage, https://github.com/sharik709/task-runner/
Project-URL: Issues, https://github.com/sharik709/task-runner/issues
Keywords: task,scheduler,automation,process
Classifier: Development Status :: 3 - Alpha
Classifier: Intended Audience :: Developers
Classifier: License :: OSI Approved :: MIT License
Classifier: Programming Language :: Python :: 3
Classifier: Programming Language :: Python :: 3.8
Classifier: Programming Language :: Python :: 3.9
Classifier: Programming Language :: Python :: 3.10
Classifier: Programming Language :: Python :: 3.11
Classifier: Programming Language :: Python :: 3.12
Classifier: Programming Language :: Python :: 3.13
Classifier: Topic :: Software Development :: Libraries :: Python Modules
Classifier: Topic :: System :: Systems Administration
Requires-Python: >=3.8
License-File: LICENSE
Requires-Dist: pydantic>=2.0.0
Requires-Dist: schedule>=1.2.0
Requires-Dist: loguru>=0.7.0
Requires-Dist: pyyaml>=6.0
Provides-Extra: dev
Requires-Dist: pytest>=8.0.0; extra == "dev"
Requires-Dist: pytest-cov>=5.0.0; extra == "dev"
Requires-Dist: black>=24.0.0; extra == "dev"
Requires-Dist: isort>=5.13.0; extra == "dev"
Requires-Dist: mypy>=1.9.0; extra == "dev"
Requires-Dist: flake8>=7.0.0; extra == "dev"
Requires-Dist: build>=1.0.0; extra == "dev"
Requires-Dist: twine>=5.0.0; extra == "dev"
Provides-Extra: mysql
Requires-Dist: mysql-connector-python>=8.0.0; extra == "mysql"
Dynamic: author
Dynamic: home-page
Dynamic: license-file
Dynamic: requires-python
